{"scores":[{"name":"Player","score":566,"date":"1-1-1"},{"name":"LeadAhead Developers","score":500,"date":"2026-04-10"},{"name":"Player","score":313,"date":"2026-4-6"},{"name":"test","score":99,"date":"2026-4-5"},{"name":"dzhzdj","score":84,"date":"2026-4-8"},{"name":"dzhzdj","score":84,"date":"2026-4-8"},{"name":"xfngxfn","score":80,"date":"2026-4-6"},{"name":"xfngxfn","score":80,"date":"2026-4-6"},{"name":"right","score":26,"date":"2026-4-6"},{"name":"right","score":26,"date":"2026-4-6"},{"name":"left","score":16,"date":"2026-4-6"},{"name":"left","score":16,"date":"2026-4-6"},{"name":"dfjn","score":0,"date":"2026-4-6"},{"name":"dfjn","score":0,"date":"2026-4-6"},{"name":"zfdhzdfhj","score":0,"date":"2026-4-8"},{"name":"zfdhzdfhj","score":0,"date":"2026-4-8"}]}